poetry_with_typer_demo/__init__.py
poetry_with_typer_demo/main.py
poetry_with_typer_demo-0.1.1.dist-info/METADATA
poetry_with_typer_demo-0.1.1.dist-info/WHEEL
poetry_with_typer_demo-0.1.1.dist-info/entry_points.txt
poetry_with_typer_demo-0.1.1.dist-info/RECORD
